eppzy/bases.py
eppzy/check.py
eppzy/connection.py
eppzy/mock_session.py
eppzy/nominate.py
eppzy/nominet.py
eppzy/rfc5730_epp.py
eppzy/rfc5731_domain.py
eppzy/rfc5732_host.py
eppzy/rfc5733_contact.py
eppzy/rfc5910_dnssec.py
eppzy/session.py
eppzy/test_utils.py
eppzy/util.py
eppzy-0.0.15.dist-info/LICENSE
eppzy-0.0.15.dist-info/METADATA
eppzy-0.0.15.dist-info/WHEEL
eppzy-0.0.15.dist-info/top_level.txt
eppzy-0.0.15.dist-info/RECORD
