Metadata-Version: 2.1
Name: eppzy
Version: 0.0.15
Summary: EPP Client Library
Home-page: https://gitlab.com/aaisp/eppzy
Author: David Honour
Author-email: david.honour@aa.net.uk
License: LGPL3
Keywords: epp
Platform: UNKNOWN
Provides-Extra: test
Requires-Dist: pytest ; extra == 'test'
Requires-Dist: pytest-flake8 ; extra == 'test'
Requires-Dist: mock ; extra == 'test'
